pwdtools/__init__.py
pwdtools/pwdgen.py
pwdtools/pwdinfo.py
pwdtools/pwdmgr.py
pwdtools/pwdmgr_clipboard.py
pwdtools/pwdmgr_cmds.py
pwdtools/pwdmgr_home.py
pwdtools/pwdmgr_pdb.py
pwdtools/pwdzxc.py
pwdtools/py.typed
pwdtools/util.py
pwdtools-1.0.6.dist-info/LICENSE
pwdtools-1.0.6.dist-info/METADATA
pwdtools-1.0.6.dist-info/WHEEL
pwdtools-1.0.6.dist-info/entry_points.txt
pwdtools-1.0.6.dist-info/top_level.txt
pwdtools-1.0.6.dist-info/zip-safe
pwdtools-1.0.6.dist-info/RECORD
