Metadata-Version: 2.1
Name: pwdtools
Version: 1.0.6
Summary: tools for password generation, management and checking
Home-page: https://ari.lt/gh/pwdtools
Author: Ari Archer
Author-email: ari@ari.lt
License: GPLv3+
Keywords: armour,passwords,password generation,password manager,password database,pdb,cryptography,hashing
Classifier: Development Status :: 5 - Production/Stable
Classifier: Intended Audience :: End Users/Desktop
Classifier: License :: OSI Approved :: GNU General Public License v3 or later (GPLv3+)
Classifier: Operating System :: OS Independent
Classifier: Programming Language :: Python :: 3
Classifier: Programming Language :: Python :: 3.9
Classifier: Programming Language :: Python :: 3.10
Classifier: Programming Language :: Python :: 3.11
Classifier: Programming Language :: Python :: 3.12
Classifier: Programming Language :: Python :: 3.13
Classifier: Topic :: Database
Classifier: Topic :: File Formats
Classifier: Topic :: Security
Classifier: Topic :: Security :: Cryptography
Classifier: Typing :: Typed
License-File: LICENSE
Requires-Dist: armour
Requires-Dist: zxcvbn
Requires-Dist: pyfzf
Requires-Dist: pyperclip
